_pelutils_c.cpython-313-darwin.so
pelutils/ticktock.py
pelutils/__init__.py
pelutils/format.py
pelutils/__version__.py
pelutils/parser.py
pelutils/jsonl.py
pelutils/datastorage.py
pelutils/tests.py
pelutils/ds/__init__.py
pelutils/ds/distributions.py
pelutils/ds/plots.py
pelutils/ds/stats.py
pelutils/_c/__init__.py
pelutils/_entry_points/__init__.py
pelutils/_entry_points/linecounter.py
pelutils/logging/_rotate.py
pelutils/logging/__init__.py
pelutils/logging/_utils.py
examples/__init__.py
examples/plots.py
examples/cli.py
pelutils-3.6.0.dist-info/RECORD
pelutils-3.6.0.dist-info/WHEEL
pelutils-3.6.0.dist-info/entry_points.txt
pelutils-3.6.0.dist-info/top_level.txt
pelutils-3.6.0.dist-info/METADATA
pelutils-3.6.0.dist-info/licenses/pelutils/_c/hashmap.c/LICENSE
