Metadata-Version: 2.4
Name: pelutils
Version: 3.6.0
Summary: Utility functions that are often useful
Home-page: https://github.com/peleiden/pelutils
Download-URL: https://pypi.org/project/pelutils/
Author: Asger Laurits Schultz, Søren Winkel Holm
Author-email: asger.s@protonmail.com, swholm@protonmail.com
License: MIT
Keywords: utility,logger,parser,profiling,plotting
Requires-Python: >=3.9
License-File: pelutils/_c/hashmap.c/LICENSE
Requires-Dist: numpy>=1.21.0
Requires-Dist: gitpython>=3.1.0
Requires-Dist: rich>=10.0.0
Requires-Dist: python-rapidjson>=1.5
Requires-Dist: py-cpuinfo>=8.0.0
Requires-Dist: psutil>=5.8.0
Requires-Dist: matplotlib>=3.3
Requires-Dist: scipy>=1.6
Requires-Dist: tqdm>=4.55
Requires-Dist: deprecated>=1.2
Provides-Extra: dev
Requires-Dist: torch>=2; extra == "dev"
Requires-Dist: pytest==8.4.2; extra == "dev"
Requires-Dist: pytest-cov==7.0.0; extra == "dev"
Requires-Dist: coveralls>=4.0.0; extra == "dev"
Requires-Dist: coverage==7.10.7; extra == "dev"
Requires-Dist: wheel; extra == "dev"
Requires-Dist: setuptools>=60.0.0; extra == "dev"
Requires-Dist: ruff==0.14.14; extra == "dev"
Requires-Dist: freezegun>=1.5; extra == "dev"
Dynamic: author
Dynamic: author-email
Dynamic: description
Dynamic: description-content-type
Dynamic: download-url
Dynamic: home-page
Dynamic: keywords
Dynamic: license
Dynamic: license-file
Dynamic: provides-extra
Dynamic: requires-dist
Dynamic: requires-python
Dynamic: summary
